networksns/__init__.py
networksns/centrality_measures.py
networksns/networksns_test.py
networksns/statistical_models.py
networksns-0.0.3.dist-info/METADATA
networksns-0.0.3.dist-info/WHEEL
networksns-0.0.3.dist-info/top_level.txt
networksns-0.0.3.dist-info/RECORD
